CONTRIBUTING.rst
HISTORY.rst
LICENSE
MANIFEST.in
README.rst
setup.cfg
setup.py
docs/Makefile
docs/conf.py
docs/contributing.rst
docs/history.rst
docs/index.rst
docs/installation.rst
docs/make.bat
docs/readme.rst
docs/usage.rst
envcheckr/__init__.py
envcheckr/envcheckr.py
envcheckr.egg-info/PKG-INFO
envcheckr.egg-info/SOURCES.txt
envcheckr.egg-info/dependency_links.txt
envcheckr.egg-info/not-zip-safe
envcheckr.egg-info/top_level.txt
tests/__init__.py
tests/env
tests/env.example
tests/test_envcheckr.py