Metadata-Version: 1.1
Name: envcheckr
Version: 0.1.0
Summary: A really simple CLI tool to check and compare two .env files for missing variables
Home-page: https://github.com/adamjace/envcheckr
Author: Adam Goldin
Author-email: adamjace@gmail.com
License: MIT license
Download-URL: https://github.com/adamjace/envcheckr/archive/0.1.tar.gz
Keywords: envcheckr,cli,env,environment,variables
Platform: UNKNOWN
Classifier: Development Status :: 2 - Pre-Alpha
Classifier: Intended Audience :: Developers
Classifier: License :: OSI Approved :: MIT License
Classifier: Natural Language :: English
Classifier: Programming Language :: Python :: 2.7
Classifier: Programming Language :: Python :: 3
Classifier: Programming Language :: Python :: 3.3
Classifier: Programming Language :: Python :: 3.4
Classifier: Programming Language :: Python :: 3.5
